vk_captcha/__init__.py
vk_captcha/__main__.py
vk_captcha/model.onnx
vk_captcha/solver.py
vk_captcha_cyrillic-2.0.3.dist-info/LICENSE
vk_captcha_cyrillic-2.0.3.dist-info/METADATA
vk_captcha_cyrillic-2.0.3.dist-info/WHEEL
vk_captcha_cyrillic-2.0.3.dist-info/top_level.txt
vk_captcha_cyrillic-2.0.3.dist-info/RECORD
